freegeniusai/README.md
freegeniusai/main.py
freegeniusai/requirements.txt
freegeniusai-0.0.1.dist-info/METADATA
freegeniusai-0.0.1.dist-info/WHEEL
freegeniusai-0.0.1.dist-info/entry_points.txt
freegeniusai-0.0.1.dist-info/top_level.txt
freegeniusai-0.0.1.dist-info/RECORD
