Metadata-Version: 2.1
Name: freegeniusai
Version: 0.0.1
Summary: FreeGenius AI, inspired by LetMeDoIt AI, offers a comprehensive suite of free, core AI features for FREE. No paid API key required.
Home-page: https://letmedoit.ai
Author: Eliran Wong
Author-email: support@letmedoit.ai
License: GNU General Public License (GPL)
Project-URL: Source, https://github.com/eliranwong/freegenius
Project-URL: Tracker, https://github.com/eliranwong/freegenius/issues
Project-URL: Documentation, https://github.com/eliranwong/freegenius/wiki
Project-URL: Funding, https://www.paypal.me/letmedoitai
Keywords: ai open llm ollama gpt mistral llama
Classifier: Development Status :: 5 - Production/Stable
Classifier: Intended Audience :: End Users/Desktop
Classifier: Topic :: Utilities
Classifier: License :: OSI Approved :: GNU General Public License v3 or later (GPLv3+)
Classifier: Programming Language :: Python :: 3.8
Classifier: Programming Language :: Python :: 3.9
Classifier: Programming Language :: Python :: 3.10
Classifier: Programming Language :: Python :: 3.11
Classifier: Programming Language :: Python :: 3.12
Requires-Python: >=3.8
Requires-Dist: ollama
